brickbundles/DriveTrain/Actuator.brick
brickbundles/DriveTrain/AutomaticClutch.brick
brickbundles/DriveTrain/CombustionEngine.brick
brickbundles/DriveTrain/Differential.brick
brickbundles/DriveTrain/EmpiricalTorqueConverter.brick
brickbundles/DriveTrain/FlexibleGear.brick
brickbundles/DriveTrain/Gear.brick
brickbundles/DriveTrain/GearBox.brick
brickbundles/DriveTrain/HingeActuator.brick
brickbundles/DriveTrain/ManualClutch.brick
brickbundles/DriveTrain/PrismaticActuator.brick
brickbundles/DriveTrain/Shaft.brick
brickbundles/DriveTrain/Signals/TorqueConverterPumpTorqueOutput.brick
brickbundles/DriveTrain/Signals/TorqueConverterTurbineTorqueOutput.brick
brickbundles/DriveTrain/Signals/TorqueMotorInput.brick
brickbundles/DriveTrain/TorqueLimitedSlipDifferential.brick
brickbundles/DriveTrain/TorqueMotor.brick
brickbundles/DriveTrain/ViscousGear.brick
brickbundles/DriveTrain/config.brick
brickbundles/Math/AffineTransform.brick
brickbundles/Math/Constants.brick
brickbundles/Math/Functions.brick
brickbundles/Math/Line.brick
brickbundles/Math/Matrix3x3.brick
brickbundles/Math/Matrix4x4.brick
brickbundles/Math/Quat.brick
brickbundles/Math/Vec2.brick
brickbundles/Math/Vec3.brick
brickbundles/Math/config.brick
brickbundles/Physics/Bodies/Body.brick
brickbundles/Physics/Bodies/Inertia.brick
brickbundles/Physics/Bodies/Kinematics.brick
brickbundles/Physics/Charges/Charge.brick
brickbundles/Physics/Charges/ContactGeometry.brick
brickbundles/Physics/Charges/LinearElasticMaterial.brick
brickbundles/Physics/Charges/Material.brick
brickbundles/Physics/Interactions/Adhesion/ConstantForceAdhesion.brick
brickbundles/Physics/Interactions/Adhesion/DefaultAdhesion.brick
brickbundles/Physics/Interactions/Clearance/ConstantAngleClearance.brick
brickbundles/Physics/Interactions/Clearance/ConstantDistanceClerance.brick
brickbundles/Physics/Interactions/Clearance/DefaultClearance.brick
brickbundles/Physics/Interactions/Dissipation/AsymmetricLimitFriction.brick
brickbundles-0.14.0.dist-info/METADATA
brickbundles-0.14.0.dist-info/WHEEL
brickbundles-0.14.0.dist-info/RECORD
